Verilog/full_adder.v
module full_adder(
    output sum,cout,
    input a,b,cin
);
    wire x,y,z;
    xor(sum,a,b,cin);
    //display(sum);
    and(x,a,b);
    and(y,b,cin);
    and(z,a,cin);
    or(cout,x,y,z);
    //display(cout);
endmodule

Verilog/full_adder_tb.v
`timescale 1ns/1ps

module full_adder_tb();
    reg a ,b ,cin;
    wire sum ,cout;

    full_adder dut(sum, cout, a ,b, cin);
    initial begin
        a=0; b=0; cin=0;#5
        $display("sum=%b, cout=%b", sum, cout);
        #100 ;
        a=0; b=0; cin=1;#5
        $display("sum=%b, cout=%b", sum, cout);
        #100 ;
        a=0; b=1; cin=1;#5
        $display("sum=%b, cout=%b", sum, cout);
        #100 ;
        a=1; b=1; cin=1;#5
        $display("sum=%b, cout=%b", sum, cout);
        #100 $finish;
    end

    initial begin
        $dumpfile("full_adder.vcd");  // create a VCD file
        $dumpvars(0, full_adder_tb);
    end

endmodule

Verilog/full_adder.vcd
$date
	Fri Dec  5 19:35:41 2025
$end
$version
	Icarus Verilog
$end
$timescale
	1ps
$end
$scope module full_adder_tb $end
$var wire 1 ! sum $end
$var wire 1 " cout $end
$var reg 1 # a $end
$var reg 1 $ b $end
$var reg 1 % cin $end
$scope module dut $end
$var wire 1 # a $end
$var wire 1 $ b $end
$var wire 1 % cin $end
$var wire 1 " cout $end
$var wire 1 ! sum $end
$var wire 1 & x $end
$var wire 1 ' y $end
$var wire 1 ( z $end
$upscope $end
$upscope $end
$enddefinitions $end
$comment Show the parameter values. $end
$dumpall
$end
#0
$dumpvars
0(
0'
0&
0%
0$
0#
0"
0!
$end
#10000
1!
1%
#20000
0%
1$
#30000
1"
0!
1'
1%
#40000
0"
0'
1!
0%
0$
1#
#50000
1"
0!
1(
1%
#60000
0(
1&
0%
1$
#70000
1!
1'
1(
1%
