Verilog/sequence_Detecter.v
module sequence_Detecter (
    input  wire a,
    input  wire clk,
    input  wire reset,
    output reg  q
);

    // State encoding
    parameter [1:0]
        S0 = 2'b00,
        S1 = 2'b01,
        S2 = 2'b10;

    reg [1:0] PS, NS;

    // -----------------------------
    // Next State Logic
    // -----------------------------
    always @(*) begin
        NS = PS; // default
        case (PS)
            S0: begin
                if (a) NS = S1;
                else   NS = S0;
            end

            S1: begin
                if (a) NS = S1;
                else   NS = S2;   // FIXED
            end

            S2: begin
                if (a) NS = S1;
                else   NS = S0;
            end

            default: NS = S0;
        endcase
    end

    // -----------------------------
    // State Register
    // -----------------------------
    always @(posedge clk) begin
        if (reset)
            PS <= S0;
        else
            PS <= NS;
    end

    // -----------------------------
    // Output Logic (Mealy)
    // -----------------------------
    always @(*) begin
        q = 1'b0; // default
        case (PS)
            S2: begin
                if (a) q = 1'b1; // detects 101
            end
            default: q = 1'b0;
        endcase
    end

endmodule

Verilog/sequence_Detecter_tb.v
`timescale 1ns/1ps

module sequence_Detecter_tb ();

  reg a;
  reg clk;
  reg reset;
  wire q;

  // Instantiate the DUT (Device Under Test)
  sequence_Detecter dut (
    .a(a),
    .clk(clk),
    .reset(reset),
    .q(q)
  );

  // Clock generation (10 ns period)
  always #5 clk = ~clk;

  initial begin
    // Initialize signals
    clk = 0;
    a = 0;
    reset = 1;

    // Dump waveform
    $dumpfile("seqdet.vcd");
    $dumpvars(0, sequence_Detecter_tb);

    // Apply reset
    #12 reset = 0;

    // Input sequence: 1 0 1 0 1 1 0 1
    #10 a = 1;
    #10 a = 0;
    #10 a = 1;  // should detect "101" → q = 1
    #10 a = 0;
    #10 a = 1;  // another "101"
    #10 a = 1;
    #10 a = 0;
    #10 a = 1;  // another "101"

    #20 $finish;
  end

endmodule

Verilog/seqdet.vcd
$date
	Sun Dec 28 20:54:13 2025
$end
$version
	Icarus Verilog
$end
$timescale
	1ps
$end
$scope module sequence_Detecter_tb $end
$var wire 1 ! q $end
$var reg 1 " a $end
$var reg 1 # clk $end
$var reg 1 $ reset $end
$scope module dut $end
$var wire 1 " a $end
$var wire 1 # clk $end
$var wire 1 $ reset $end
$var parameter 2 % S0 $end
$var parameter 2 & S1 $end
$var parameter 2 ' S2 $end
$var reg 2 ( NS [1:0] $end
$var reg 2 ) PS [1:0] $end
$var reg 1 ! q $end
$upscope $end
$upscope $end
$enddefinitions $end
$comment Show the parameter values. $end
$dumpall
b10 '
b1 &
b0 %
$end
#0
$dumpvars
bx )
b0 (
1$
0#
0"
0!
$end
#5000
b0 )
1#
#10000
0#
#12000
0$
#15000
1#
#20000
0#
#22000
b1 (
1"
#25000
b1 )
1#
#30000
0#
#32000
b10 (
0"
#35000
b0 (
b10 )
1#
#40000
0#
#42000
1!
b1 (
1"
#45000
0!
b1 )
1#
#50000
0#
#52000
b10 (
0"
#55000
b0 (
b10 )
1#
#60000
0#
#62000
1!
b1 (
1"
#65000
0!
b1 )
1#
#70000
0#
#75000
1#
#80000
0#
#82000
b10 (
0"
#85000
b0 (
b10 )
1#
#90000
0#
#92000
1!
b1 (
1"
#95000
0!
b1 )
1#
